base_changer/__init__.py
base_changer-0.0.6.dist-info/METADATA
base_changer-0.0.6.dist-info/WHEEL
base_changer-0.0.6.dist-info/top_level.txt
base_changer-0.0.6.dist-info/RECORD
