Metadata-Version: 2.1
Name: base-changer
Version: 0.0.6
Summary: Number System converter
Author: Harsh Gupta
Author-email: harshnkgupta@gmail.com
